camelsnake.py
camelsnake-0.0.2.dist-info/METADATA
camelsnake-0.0.2.dist-info/WHEEL
camelsnake-0.0.2.dist-info/licenses/LICENSE.md
camelsnake-0.0.2.dist-info/RECORD
