Metadata-Version: 2.1
Name: camelsnake
Version: 0.0.2
Summary: camelsnake is a Python library for converting between camel case and snake case strings
Project-URL: Homepage, https://github.com/nerandell/camelsnake
Project-URL: Bug Tracker, https://github.com/nerandell/camelsnake/issues
Author-email: Ankit Chandawala <ankitchandawala@gmail.com>
License-File: LICENSE.md
Classifier: License :: OSI Approved :: MIT License
Classifier: Operating System :: OS Independent
Classifier: Programming Language :: Python :: 3
Requires-Python: >=3.7
